[
  {
    "url": "",
    "country": "ʿAdan,Adan",
    "capital": "Aden",
    "shapes": "",
    "card": "https://upload.wikimedia.org/wikipedia/commons/thumb/c/c1/Adan_in_Yemen.svg/800px-Adan_in_Yemen.svg.png"
  },
  {
    "url": "",
    "country": "ʿAmrān,Amran",
    "capital": "ʿAmrān,Amran",
    "shapes": "",
    "card": "https://upload.wikimedia.org/wikipedia/commons/thumb/b/be/Amran_in_Yemen.svg/800px-Amran_in_Yemen.svg.png"
  },
  {
    "url": "",
    "country": "Abyan",
    "capital": "Zindschibar",
    "shapes": "",
    "card": "https://upload.wikimedia.org/wikipedia/commons/thumb/9/9b/Abyan_in_Yemen.svg/800px-Abyan_in_Yemen.svg.png"
  },
  {
    "url": "",
    "country": "ad-Dāliʿ,ad Dali",
    "capital": "ad-Dāliʿ,ad Dali",
    "shapes": "",
    "card": "https://upload.wikimedia.org/wikipedia/commons/thumb/2/2a/Ad_Dali%27_in_Yemen.svg/800px-Ad_Dali%27_in_Yemen.svg.png"
  },
  {
    "url": "",
    "country": "al-Baidā',al Baida",
    "capital": "al-Baidā',al Baida",
    "shapes": "",
    "card": "https://upload.wikimedia.org/wikipedia/commons/thumb/0/03/Al_Bayda%27_in_Yemen.svg/800px-Al_Bayda%27_in_Yemen.svg.png"
  },
  {
    "url": "",
    "country": "al-Hudaida,al Hudaida",
    "capital": "al-Hudaida,al Hudaida",
    "shapes": "",
    "card": "https://upload.wikimedia.org/wikipedia/commons/thumb/d/d1/Al_Hudaydah_in_Yemen.svg/800px-Al_Hudaydah_in_Yemen.svg.png"
  },
  {
    "url": "",
    "country": "al-Dschauf,al Dschauf",
    "capital": "al-Hazm,al Hazm",
    "shapes": "",
    "card": "https://upload.wikimedia.org/wikipedia/commons/thumb/5/52/Al_Jawf_in_Yemen.svg/800px-Al_Jawf_in_Yemen.svg.png"
  },
  {
    "url": "",
    "country": "al-Mahra,al Mahra",
    "capital": "al-Ghaida,al Ghaida",
    "shapes": "",
    "card": "https://upload.wikimedia.org/wikipedia/commons/thumb/1/12/Al_Mahrah_in_Yemen.svg/800px-Al_Mahrah_in_Yemen.svg.png"
  },
  {
    "url": "",
    "country": "al-Mahwīt,al Mahwit",
    "capital": "al-Mahwīt,al Mahwit",
    "shapes": "",
    "card": "https://upload.wikimedia.org/wikipedia/commons/thumb/5/56/Al_Mahwit_in_Yemen.svg/800px-Al_Mahwit_in_Yemen.svg.png"
  },
  {
    "url": "",
    "country": "Sanaa",
    "capital": "Sanaa",
    "shapes": "",
    "card": "https://upload.wikimedia.org/wikipedia/commons/thumb/3/38/Amanat_Al_Asimah_in_Yemen.svg/1280px-Amanat_Al_Asimah_in_Yemen.svg.png"
  },
  {
    "url": "",
    "country": "Dhamār,Dhamar",
    "capital": "Dhamār,Dhamar",
    "shapes": "",
    "card": "https://upload.wikimedia.org/wikipedia/commons/thumb/b/bb/Dhamar_in_Yemen.svg/800px-Dhamar_in_Yemen.svg.png"
  },
  {
    "url": "",
    "country": "Hadramaut",
    "capital": "al-Mukalla,al Mukalla",
    "shapes": "",
    "card": "https://upload.wikimedia.org/wikipedia/commons/thumb/c/c5/Hadramaut_in_Yemen.svg/800px-Hadramaut_in_Yemen.svg.png"
  },
  {
    "url": "",
    "country": "Haddscha",
    "capital": "Haddscha",
    "shapes": "",
    "card": "https://upload.wikimedia.org/wikipedia/commons/thumb/9/9f/Hajjah_in_Yemen.svg/800px-Hajjah_in_Yemen.svg.png"
  },
  {
    "url": "",
    "country": "Ibb",
    "capital": "Ibb",
    "shapes": "",
    "card": "https://upload.wikimedia.org/wikipedia/commons/thumb/a/aa/Ibb_in_Yemen.svg/800px-Ibb_in_Yemen.svg.png"
  },
  {
    "url": "",
    "country": "Lahidsch",
    "capital": "Lahidsch",
    "shapes": "",
    "card": "https://upload.wikimedia.org/wikipedia/commons/thumb/4/43/Lahij_in_Yemen.svg/800px-Lahij_in_Yemen.svg.png"
  },
  {
    "url": "",
    "country": "Ma'rib,Ma rib",
    "capital": "Ma'rib,Ma rib",
    "shapes": "",
    "card": "https://upload.wikimedia.org/wikipedia/commons/thumb/1/12/Ma%27rib_in_Yemen.svg/800px-Ma%27rib_in_Yemen.svg.png"
  },
  {
    "url": "",
    "country": "Raima",
    "capital": "al-Dschabīn,al Dschabin",
    "shapes": "",
    "card": "https://upload.wikimedia.org/wikipedia/commons/thumb/f/f5/Raymah_in_Yemen.svg/800px-Raymah_in_Yemen.svg.png"
  },
  {
    "url": "",
    "country": "Saʿda,Sa da",
    "capital": "Saʿda,Sa da",
    "shapes": "",
    "card": "https://upload.wikimedia.org/wikipedia/commons/thumb/8/8a/Sa%27dah_in_Yemen.svg/800px-Sa%27dah_in_Yemen.svg.png"
  },
  {
    "url": "",
    "country": "Sanaa",
    "capital": "Sanaa",
    "shapes": "",
    "card": "https://upload.wikimedia.org/wikipedia/commons/thumb/2/2c/Sana%27a_in_Yemen.svg/800px-Sana%27a_in_Yemen.svg.png"
  },
  {
    "url": "",
    "country": "Schabwa",
    "capital": "ʿAtaq,Ataq",
    "shapes": "",
    "card": "https://upload.wikimedia.org/wikipedia/commons/thumb/1/1b/Shabwah_in_Yemen.svg/800px-Shabwah_in_Yemen.svg.png"
  },
  {
    "url": "",
    "country": "Taʿizz,Ta izz",
    "capital": "Taʿizz,Ta izz",
    "shapes": "",
    "card": "https://upload.wikimedia.org/wikipedia/commons/thumb/8/8a/Ta%27izz_in_Yemen.svg/800px-Ta%27izz_in_Yemen.svg.png"
  },
  {
    "url": "",
    "country": "Sokotra",
    "capital": "Hadibu",
    "shapes": "",
    "card": "https://upload.wikimedia.org/wikipedia/commons/thumb/1/17/Socotra_in_Yemen.svg/800px-Socotra_in_Yemen.svg.png"
  }
]